anypay_wrapper/__init__.py
anypay_wrapper/pay_api.py
anypay_wrapper/api_types/__init__.py
anypay_wrapper/api_types/paying_types.py
anypay_wrapper/api_types/response_types.py
anypay_wrapper-1.0.0.dist-info/METADATA
anypay_wrapper-1.0.0.dist-info/WHEEL
anypay_wrapper-1.0.0.dist-info/top_level.txt
anypay_wrapper-1.0.0.dist-info/RECORD
