Metadata-Version: 2.1
Name: anypay-wrapper
Version: 1.0.0
Summary: AnyPay API Wrapper
Home-page: https://github.com/MagistrUMDev/anypay_api
Author: MagistrUMDev
License: UNKNOWN
Platform: UNKNOWN
Classifier: Programming Language :: Python :: 3
Classifier: License :: OSI Approved :: MIT License
Classifier: Operating System :: OS Independent
Requires-Python: >=3.9
Requires-Dist: aiohttp (>=3.8.3)
